{
  "group": "densemobdrops",
  "type": "minecraft:crafting_shapeless",
  "ingredients": [
    {
      "item": "densemobdrops:rotten_flesh_4"
    },
    {
      "item": "densemobdrops:rotten_flesh_4"
    },
    {
      "item": "densemobdrops:rotten_flesh_4"
    },
    {
      "item": "densemobdrops:rotten_flesh_4"
    },
    {
      "item": "densemobdrops:rotten_flesh_4"
    },
    {
      "item": "densemobdrops:rotten_flesh_4"
    },
    {
      "item": "densemobdrops:rotten_flesh_4"
    },
    {
      "item": "densemobdrops:rotten_flesh_4"
    },
    {
      "item": "densemobdrops:rotten_flesh_4"
    }
  ],
  "result": {
    "item": "densemobdrops:rotten_flesh_5",
    "count": 1
  }
}